aiogram_utils/__init__.py
aiogram_utils/__main__.py
aiogram_utils/content_types.py
aiogram_utils/errors.py
aiogram_utils/filters/__init__.py
aiogram_utils/filters/buttons.py
aiogram_utils/filters/storage.py
aiogram_utils/formatting.py
aiogram_utils/keyboards.py
aiogram_utils/middlewares/__init__.py
aiogram_utils/middlewares/answer_any_query.py
aiogram_utils/mongoengine.py
aiogram_utils/storage_proxy.py
aiogram_utils/task_manager.py
aiogram_utils-0.1.3.dist-info/WHEEL
aiogram_utils-0.1.3.dist-info/METADATA
aiogram_utils-0.1.3.dist-info/RECORD
